{
  "id": "GST_1774242251129",
  "status": "CLOSED",
  "entry_time": "2026-03-23T02:04:11.129970Z",
  "entry_timestamp": 1774242251.12997,
  "entry_price": 67868.97,
  "direction": "SELL",
  "veto_reason": "WAIT: HORIZONTAL_SUPPORT_VETO (Level=67848, Valleys=12)",
  "signal_strength": -0.37028790247369353,
  "confidence": 0.5025277979020263,
  "coherence": 0.4049395465670847,
  "phi": 0.022104016412029002,
  "sl_price": 67954.90491763291,
  "tp_price": 67697.10016473419,
  "close_time": "2026-03-23T02:07:47.298452Z",
  "close_price": 67958.59,
  "result": "TRUE_NEGATIVE",
  "cycle_code": "CYC003_20260323",
  "candle_pos": "23",
  "swarm_intelligence": {
    "bull_agents": [
      "MomentumAgent",
      "SRAgent",
      "LiquidationVacuumAgent",
      "StopHunterAgent",
      "InformationEntropyAgent",
      "MultiScaleFractalResonance",
      "CppTickEntropyAgent",
      "FVGAgent",
      "OrderBlockAgent",
      "ChartStructureAgent",
      "PriceGravityAgent",
      "HexMatrix",
      "BlackSwanEVT",
      "ChaosRegime",
      "LiquidStateAgent",
      "RogueWaveNLSE",
      "HolographicEntanglement",
      "StrangeAttractorFolding",
      "FourierSpectral",
      "RandomMatrixTheory",
      "DarkMatterGravity"
    ],
    "bear_agents": [
      "TrendAgent",
      "MicrostructureAgent",
      "LiquiditySiphonAgent",
      "SentimentFearGreedAgent",
      "OnChainPressureAgent",
      "GameTheoryNashAgent",
      "CppFractalAgent",
      "AggressivenessAgent",
      "PriceVelocityAgent",
      "PressureMatrix",
      "TemporalTrend",
      "Thermodynamic",
      "FeynmanPath",
      "RiemannianManifold",
      "QuantumSpin",
      "ChaosFractalDim",
      "MorphogeneticResonance",
      "SpectralInformationFlux",
      "SingularSpectrumAnalysis",
      "KripkeSemantics",
      "KolmogorovInertia",
      "CrashVelocityDetector"
    ],
    "neutral_agents": [
      "VolumeAgent",
      "VolatilityAgent",
      "StatisticalAgent",
      "FractalAgent",
      "DivergenceAgent",
      "TimeWarpAgent",
      "RetailPsychologyAgent",
      "CandleAnatomyAgent",
      "ExplosionDetectorAgent",
      "OscillationWaveAgent",
      "MarketTransition",
      "SessionDynamics",
      "WyckoffMatrix",
      "CRTAgent",
      "TBSAgent",
      "MarketIntuition",
      "TensorMPS",
      "SpikingPulse",
      "MeanFieldGame",
      "HolographicManifold",
      "InformationGeometry",
      "QuantumSuperposition",
      "RGScalingInvariance"
    ]
  },
  "snapshot": {
    "regime": "UNKNOWN",
    "atr": 57.28994508860518,
    "metadata": {
      "tick_velocity": 3.9789909279006843,
      "v_pulse_detected": false,
      "shannon_entropy": 0.0,
      "jounce": 0.0
    }
  }
}