{
    "ticket": 0,
    "timestamp_entry": 1773948645.4965014,
    "action": "SELL",
    "signal": -0.1951684406788008,
    "confidence": 0.6024446656484947,
    "reasoning": "SELL signal=-0.195 conf=0.60 coherence=0.35 regime=CREEPING_BULL ATR=197.08 RR=2.35 | [PHASE_50_STRIKE: SELL] | Quantum: SIGNAL=-0.390 | CONF=0.86 | \u03a6=0.19 | COH=35.24% | BEAR: SingularSpectrumAnalysis, KripkeSemantics, KolmogorovInertia [!LOW_COHERENCE_DAMPENING!] | MC[score=+0.062 WP=50.7% EV=+5.19 CVaR=-350.00 sim=41.7ms]",
    "regime": "CREEPING_BULL",
    "lot_size": 0.01,
    "entry_price": 70159.57,
    "stop_loss": 70509.57,
    "take_profit": 69337.83495067811,
    "snapshot": {
        "price": 70160.07,
        "atr": 102.08526701085026,
        "phi": 0.19087341451575437,
        "kl_div": 0.0
    }
}