{
  "id": "GST_1774396394761",
  "status": "CLOSED",
  "entry_time": "2026-03-24T20:53:14.761411Z",
  "entry_timestamp": 1774396394.761411,
  "entry_price": 70085.91,
  "direction": "BUY",
  "veto_reason": "WAIT: ELITE_DIVERGENCE_VETO (Swarm=-1.0, Elite_Sum=1.0)",
  "signal_strength": 0.4722636664535229,
  "confidence": 0.5206011283910319,
  "coherence": 0.4042530272055432,
  "phi": 0.13586009699766463,
  "sl_price": 69956.79295819938,
  "tp_price": 70344.14408360123,
  "close_time": "2026-03-24T21:13:49.096296Z",
  "close_price": 69931.04,
  "result": "TRUE_NEGATIVE",
  "cycle_code": "CYC001_20260324",
  "candle_pos": "40_4",
  "swarm_intelligence": {
    "bull_agents": [
      "TrendAgent",
      "MomentumAgent",
      "SRAgent",
      "MultiScaleFractalResonance",
      "MacroBiasAgent",
      "CppFractalAgent",
      "FVGAgent",
      "BOSAgent",
      "PriceGravityAgent",
      "PriceVelocityAgent",
      "OscillationWaveAgent",
      "HexMatrix",
      "TBSAgent",
      "ChaosRegime",
      "RogueWaveNLSE",
      "HolographicEntanglement",
      "KinematicJounce",
      "QuantumSpin",
      "ChaosFractalDim",
      "FourierSpectral",
      "SpectralInformationFlux",
      "SingularSpectrumAnalysis",
      "RandomMatrixTheory",
      "DarkMatterGravity",
      "CrashVelocityDetector"
    ],
    "bear_agents": [
      "MicrostructureAgent",
      "StatisticalAgent",
      "DivergenceAgent",
      "LiquidationVacuumAgent",
      "LiquiditySiphonAgent",
      "SentimentFearGreedAgent",
      "OnChainPressureAgent",
      "GameTheoryNashAgent",
      "ChartStructureAgent",
      "CandleAnatomyAgent",
      "AggressivenessAgent",
      "PressureMatrix",
      "BlackSwanEVT",
      "Thermodynamic",
      "FeynmanPath",
      "RiemannianManifold",
      "StrangeAttractorFolding",
      "KripkeSemantics",
      "KolmogorovInertia"
    ],
    "neutral_agents": [
      "VolumeAgent",
      "VolatilityAgent",
      "FractalAgent",
      "TimeWarpAgent",
      "RetailPsychologyAgent",
      "ExplosionDetectorAgent",
      "MarketTransition",
      "SessionDynamics",
      "TemporalTrend",
      "WyckoffMatrix",
      "CRTAgent",
      "MarketIntuition",
      "TensorMPS",
      "SpikingPulse",
      "MeanFieldGame",
      "HolographicManifold",
      "InformationGeometry",
      "QuantumSuperposition",
      "RGScalingInvariance"
    ]
  },
  "snapshot": {
    "regime": "CREEPING_BULL",
    "atr": 86.07802786707715,
    "metadata": {
      "tick_velocity": 3.9485114111979787,
      "v_pulse_detected": false,
      "shannon_entropy": 5.367956421751733,
      "jounce": 3.889524855773242
    }
  }
}