{
  "id": "GST_1774633201092",
  "status": "CLOSED",
  "entry_time": "2026-03-27T14:40:01.092694Z",
  "entry_timestamp": 1774633201.092694,
  "entry_price": 65767.41,
  "direction": "SELL",
  "veto_reason": "WAIT: MINIMUM_CONSENSUS_VETO (SELL has only 1 supporting agents, need 3)",
  "signal_strength": -0.24023573865415765,
  "confidence": 0.5339023315851562,
  "coherence": 0.43378083939495254,
  "phi": 0.19235577369167337,
  "sl_price": 65894.34650068384,
  "tp_price": 65513.53699863233,
  "close_time": "2026-03-27T14:50:59.326553Z",
  "close_price": 66033.04,
  "result": "TRUE_NEGATIVE",
  "cycle_code": "CYC005_20260327",
  "candle_pos": "34_3",
  "swarm_intelligence": {
    "bull_agents": [
      "StatisticalAgent",
      "SRAgent",
      "StopHunterAgent",
      "QuantumEntanglement",
      "MacroBiasAgent",
      "PremiumDiscountAgent",
      "ChartStructureAgent",
      "CandleAnatomyAgent",
      "PriceGravityAgent",
      "SessionDynamics",
      "HexMatrix",
      "RogueWaveNLSE",
      "HolographicEntanglement",
      "HolographicMemory",
      "StrangeAttractorFolding",
      "LiquidityGraph",
      "RandomMatrixTheory",
      "DarkMatterGravity",
      "PrigogineDissipative"
    ],
    "bear_agents": [
      "TrendAgent",
      "MomentumAgent",
      "MicrostructureAgent",
      "LiquidationVacuumAgent",
      "LiquiditySiphonAgent",
      "MultiScaleFractalResonance",
      "SentimentFearGreedAgent",
      "OnChainPressureAgent",
      "GameTheoryNashAgent",
      "CppFractalAgent",
      "FVGAgent",
      "BOSAgent",
      "OscillationWaveAgent",
      "PressureMatrix",
      "TBSAgent",
      "BlackSwanEVT",
      "Thermodynamic",
      "FeynmanPath",
      "RiemannianManifold",
      "QuantumSpin",
      "ChaosFractalDim",
      "MorphogeneticResonance",
      "NexusAgent",
      "FourierSpectral",
      "SpectralInformationFlux",
      "SingularSpectrumAnalysis",
      "KripkeSemantics",
      "Supersymmetry",
      "RiemannianRicci",
      "KolmogorovInertia"
    ],
    "neutral_agents": [
      "VolumeAgent",
      "VolatilityAgent",
      "FractalAgent",
      "DivergenceAgent",
      "TimeWarpAgent",
      "AggressivenessAgent",
      "ExplosionDetectorAgent",
      "PriceVelocityAgent",
      "MarketTransition",
      "TemporalTrend",
      "WyckoffMatrix",
      "CRTAgent",
      "MarketIntuition",
      "TensorMPS",
      "SpikingPulse",
      "MeanFieldGame",
      "ChaosRegime",
      "HolographicManifold",
      "InformationGeometry",
      "QuantumSuperposition",
      "RGScalingInvariance"
    ]
  },
  "snapshot": {
    "regime": "DRIFTING_BEAR",
    "atr": 84.62433378922488,
    "metadata": {
      "tick_velocity": 3.969829297340214,
      "v_pulse_detected": false,
      "shannon_entropy": 4.533901442000112,
      "jounce": 1.9564521641921506
    }
  }
}