{
  "id": "GST_1774236304328",
  "status": "CLOSED",
  "entry_time": "2026-03-23T00:25:04.328643Z",
  "entry_timestamp": 1774236304.328643,
  "entry_price": 68018.61,
  "direction": "BUY",
  "veto_reason": "WAIT: SYNERGY_VETO (Φ=0.016)",
  "signal_strength": 0.207416282797152,
  "confidence": 0.5034203493341034,
  "coherence": 0.3925535135387087,
  "phi": 0.016242581435778867,
  "sl_price": 67912.31148919537,
  "tp_price": 68231.20702160927,
  "close_time": "2026-03-23T00:31:41.313529Z",
  "close_price": 67912.29,
  "result": "TRUE_NEGATIVE",
  "cycle_code": "CYC001_20260323",
  "candle_pos": "14_1",
  "swarm_intelligence": {
    "bull_agents": [
      "LiquidationVacuumAgent",
      "InformationEntropyAgent",
      "CrossScaleConvergenceAgent",
      "MultiScaleFractalResonance",
      "CppTickEntropyAgent",
      "PriceGravityAgent",
      "AggressivenessAgent",
      "PriceVelocityAgent",
      "ChaosRegime",
      "RogueWaveNLSE",
      "HolographicEntanglement",
      "QuantumSpin",
      "ChaosFractalDim",
      "LiquidityGraph",
      "SpectralInformationFlux",
      "SingularSpectrumAnalysis",
      "KripkeSemantics",
      "DarkMatterGravity",
      "RiemannianRicci"
    ],
    "bear_agents": [
      "TrendAgent",
      "MomentumAgent",
      "MicrostructureAgent",
      "StopHunterAgent",
      "LiquiditySiphonAgent",
      "SentimentFearGreedAgent",
      "OnChainPressureAgent",
      "GameTheoryNashAgent",
      "CppFractalAgent",
      "FVGAgent",
      "OrderBlockAgent",
      "BOSAgent",
      "ChartStructureAgent",
      "CandleAnatomyAgent",
      "PressureMatrix",
      "TemporalTrend",
      "HexMatrix",
      "BlackSwanEVT",
      "Thermodynamic",
      "RiemannianManifold",
      "NonBondedRepulsion",
      "StrangeAttractorFolding",
      "FourierSpectral",
      "RandomMatrixTheory",
      "KolmogorovInertia",
      "CrashVelocityDetector"
    ],
    "neutral_agents": [
      "VolumeAgent",
      "VolatilityAgent",
      "StatisticalAgent",
      "FractalAgent",
      "SRAgent",
      "DivergenceAgent",
      "TimeWarpAgent",
      "RetailPsychologyAgent",
      "PremiumDiscountAgent",
      "ExplosionDetectorAgent",
      "OscillationWaveAgent",
      "MarketTransition",
      "SessionDynamics",
      "WyckoffMatrix",
      "CRTAgent",
      "TBSAgent",
      "MarketIntuition",
      "TensorMPS",
      "SpikingPulse",
      "MeanFieldGame",
      "FeynmanPath",
      "HolographicManifold",
      "InformationGeometry",
      "QuantumSuperposition",
      "RGScalingInvariance"
    ]
  },
  "snapshot": {
    "regime": "DRIFTING_BEAR",
    "atr": 70.8656738697541,
    "metadata": {
      "tick_velocity": 3.904419803217242,
      "v_pulse_detected": false,
      "shannon_entropy": 0.0,
      "jounce": 0.0
    }
  }
}