{
  "id": "GST_1774409763663",
  "status": "CLOSED",
  "entry_time": "2026-03-25T00:36:03.663699Z",
  "entry_timestamp": 1774409763.663699,
  "entry_price": 70795.21,
  "direction": "BUY",
  "veto_reason": "WAIT: MICRO_MOMENTUM_VETO (Last 3 M1 candles strongly oppose signal)",
  "signal_strength": 0.3977606113489138,
  "confidence": 0.5563345032887909,
  "coherence": 0.3328293937795762,
  "phi": 0.22266473383878552,
  "sl_price": 70712.63586751529,
  "tp_price": 70960.35826496943,
  "close_time": "2026-03-25T00:42:37.589892Z",
  "close_price": 70977.22,
  "result": "FALSE_NEGATIVE",
  "cycle_code": "CYC001_20260325",
  "candle_pos": "37",
  "swarm_intelligence": {
    "bull_agents": [
      "TrendAgent",
      "LiquidationVacuumAgent",
      "InformationEntropyAgent",
      "CrossScaleConvergenceAgent",
      "MultiScaleFractalResonance",
      "QuantumEntanglement",
      "MacroBiasAgent",
      "CppFractalAgent",
      "CppTickEntropyAgent",
      "FVGAgent",
      "AggressivenessAgent",
      "PriceVelocityAgent",
      "OscillationWaveAgent",
      "HexMatrix",
      "TBSAgent",
      "FeynmanPath",
      "ChaosRegime",
      "RogueWaveNLSE",
      "HolographicEntanglement",
      "NonBondedRepulsion",
      "QuantumSpin",
      "ChaosFractalDim",
      "QuantumTunnelingProb",
      "NexusAgent",
      "FourierSpectral",
      "SpectralInformationFlux",
      "EigenvectorCentrality",
      "SingularSpectrumAnalysis",
      "DarkMatterGravity",
      "QuantumDirectionalInference",
      "RiemannianRicci",
      "PredictiveVidenteAgent"
    ],
    "bear_agents": [
      "MicrostructureAgent",
      "StatisticalAgent",
      "SRAgent",
      "ReflexivityAgent",
      "StopHunterAgent",
      "LiquiditySiphonAgent",
      "SentimentFearGreedAgent",
      "OnChainPressureAgent",
      "GameTheoryNashAgent",
      "PremiumDiscountAgent",
      "ChartStructureAgent",
      "CandleAnatomyAgent",
      "PressureMatrix",
      "TemporalTrend",
      "BlackSwanEVT",
      "Thermodynamic",
      "RiemannianManifold",
      "StrangeAttractorFolding",
      "RandomMatrixTheory",
      "PrigogineDissipative",
      "KolmogorovInertia",
      "OrnsteinUhlenbeck"
    ],
    "neutral_agents": [
      "MomentumAgent",
      "VolumeAgent",
      "VolatilityAgent",
      "FractalAgent",
      "DivergenceAgent",
      "TimeWarpAgent",
      "RetailPsychologyAgent",
      "PriceGravityAgent",
      "ExplosionDetectorAgent",
      "MarketTransition",
      "SessionDynamics",
      "WyckoffMatrix",
      "CRTAgent",
      "MarketIntuition",
      "SpikingPulse",
      "MeanFieldGame",
      "HolographicManifold",
      "InformationGeometry",
      "QuantumSuperposition",
      "RGScalingInvariance"
    ]
  },
  "snapshot": {
    "regime": "CREEPING_BULL",
    "atr": 55.04942165647438,
    "metadata": {
      "tick_velocity": 3.9783577339274343,
      "v_pulse_detected": false,
      "shannon_entropy": 5.395224474637456,
      "jounce": -3.560500989048329
    }
  }
}