{
  "id": "GST_1774634490658",
  "status": "CLOSED",
  "entry_time": "2026-03-27T15:01:30.658666Z",
  "entry_timestamp": 1774634490.658666,
  "entry_price": 66174.26,
  "direction": "SELL",
  "veto_reason": "WAIT: MINIMUM_CONSENSUS_VETO (SELL has only 2 supporting agents, need 3)",
  "signal_strength": -0.27790987388287136,
  "confidence": 0.5195240496825309,
  "coherence": 0.37390211740972373,
  "phi": 0.018931355622035233,
  "sl_price": 66288.40508509352,
  "tp_price": 65945.96982981295,
  "close_time": "2026-03-27T15:22:56.018828Z",
  "close_price": 65945.44,
  "result": "FALSE_NEGATIVE",
  "cycle_code": "CYC006_20260327",
  "candle_pos": "7_4",
  "swarm_intelligence": {
    "bull_agents": [
      "MomentumAgent",
      "SRAgent",
      "MacroBiasAgent",
      "CppFractalAgent",
      "PremiumDiscountAgent",
      "PriceGravityAgent",
      "PriceVelocityAgent",
      "SessionDynamics",
      "TemporalTrend",
      "HexMatrix",
      "ICTAdvanced",
      "DarkMass",
      "PheromoneFieldAgent",
      "HolographicEntanglement",
      "QuantumSpin",
      "ChaosFractalDim",
      "LiquidityGraph",
      "FourierSpectral",
      "SpectralInformationFlux",
      "SingularSpectrumAnalysis",
      "RandomMatrixTheory",
      "DarkMatterGravity",
      "CrashVelocityDetector"
    ],
    "bear_agents": [
      "TrendAgent",
      "MicrostructureAgent",
      "DivergenceAgent",
      "LiquidationVacuumAgent",
      "StopHunterAgent",
      "LiquiditySiphonAgent",
      "MultiScaleFractalResonance",
      "SentimentFearGreedAgent",
      "OnChainPressureAgent",
      "GameTheoryNashAgent",
      "FVGAgent",
      "OrderBlockAgent",
      "ChartStructureAgent",
      "CandleAnatomyAgent",
      "AggressivenessAgent",
      "PressureMatrix",
      "BlackSwanEVT",
      "Thermodynamic",
      "FeynmanPath",
      "RiemannianManifold",
      "NonBondedRepulsion",
      "StrangeAttractorFolding",
      "NexusAgent",
      "KripkeSemantics",
      "KolmogorovInertia"
    ],
    "neutral_agents": [
      "VolumeAgent",
      "VolatilityAgent",
      "StatisticalAgent",
      "FractalAgent",
      "TimeWarpAgent",
      "RetailPsychologyAgent",
      "ExplosionDetectorAgent",
      "OscillationWaveAgent",
      "MarketTransition",
      "WyckoffMatrix",
      "CRTAgent",
      "TBSAgent",
      "MarketIntuition",
      "TensorMPS",
      "SpikingPulse",
      "MeanFieldGame",
      "ChaosRegime",
      "HolographicManifold",
      "InformationGeometry",
      "QuantumSuperposition",
      "RGScalingInvariance"
    ]
  },
  "snapshot": {
    "regime": "DRIFTING_BEAR",
    "atr": 76.09672339568259,
    "metadata": {
      "tick_velocity": 2.9479393903661344,
      "v_pulse_detected": false,
      "shannon_entropy": 4.601535322102543,
      "jounce": 15.12241054613936
    }
  }
}