{
  "id": "GST_1774623073944",
  "status": "CLOSED",
  "entry_time": "2026-03-27T11:51:13.944031Z",
  "entry_timestamp": 1774623073.944031,
  "entry_price": 66728.87,
  "direction": "BUY",
  "veto_reason": "WAIT: TREND_PROTECTION_VETO (Requires Φ>0.20 & Sig>0.40 to fade DRIFTING_BEAR)",
  "signal_strength": 0.3573325987800614,
  "confidence": 0.5078886103893951,
  "coherence": 0.3302953762650061,
  "phi": 0.025530433687002616,
  "sl_price": 66657.97323721182,
  "tp_price": 66870.66352557637,
  "close_time": "2026-03-27T12:05:53.637697Z",
  "close_price": 66591.05,
  "result": "TRUE_NEGATIVE",
  "cycle_code": "CYC002_20260327",
  "candle_pos": "5_1",
  "swarm_intelligence": {
    "bull_agents": [
      "MomentumAgent",
      "HarmonicResonanceAgent",
      "MacroBiasAgent",
      "CppFractalAgent",
      "FVGAgent",
      "PremiumDiscountAgent",
      "PriceGravityAgent",
      "PriceVelocityAgent",
      "HexMatrix",
      "TBSAgent",
      "ChaosRegime",
      "PheromoneFieldAgent",
      "RogueWaveNLSE",
      "HolographicEntanglement",
      "ChaosFractalDim",
      "StrangeAttractorFolding",
      "SpectralInformationFlux",
      "SingularSpectrumAnalysis",
      "KripkeSemantics",
      "DarkMatterGravity",
      "RiemannianRicci",
      "PredictiveVidenteAgent"
    ],
    "bear_agents": [
      "TrendAgent",
      "MicrostructureAgent",
      "LiquidationVacuumAgent",
      "LiquiditySiphonAgent",
      "InformationEntropyAgent",
      "MultiScaleFractalResonance",
      "SentimentFearGreedAgent",
      "OnChainPressureAgent",
      "GameTheoryNashAgent",
      "CppTickEntropyAgent",
      "BOSAgent",
      "CandleAnatomyAgent",
      "PressureMatrix",
      "BlackSwanEVT",
      "Thermodynamic",
      "FeynmanPath",
      "RiemannianManifold",
      "QuantumSpin",
      "NexusAgent",
      "FourierSpectral",
      "RandomMatrixTheory",
      "KolmogorovInertia",
      "CrashVelocityDetector"
    ],
    "neutral_agents": [
      "VolumeAgent",
      "VolatilityAgent",
      "StatisticalAgent",
      "FractalAgent",
      "SRAgent",
      "DivergenceAgent",
      "TimeWarpAgent",
      "ChartStructureAgent",
      "AggressivenessAgent",
      "ExplosionDetectorAgent",
      "OscillationWaveAgent",
      "MarketTransition",
      "SessionDynamics",
      "TemporalTrend",
      "WyckoffMatrix",
      "CRTAgent",
      "MarketIntuition",
      "TensorMPS",
      "SpikingPulse",
      "MeanFieldGame",
      "HolographicManifold",
      "InformationGeometry",
      "QuantumSuperposition",
      "RGScalingInvariance"
    ]
  },
  "snapshot": {
    "regime": "DRIFTING_BEAR",
    "atr": 47.264508525456115,
    "metadata": {
      "tick_velocity": 4.108125872976748,
      "v_pulse_detected": false,
      "shannon_entropy": 4.490828126180098,
      "jounce": -6.251552304183883
    }
  }
}