{
  "id": "GST_1774622637048",
  "status": "CLOSED",
  "entry_time": "2026-03-27T11:43:57.048593Z",
  "entry_timestamp": 1774622637.048593,
  "entry_price": 66733.8,
  "direction": "BUY",
  "veto_reason": "WAIT: STARTUP_COOLDOWN(1s/120.0s)",
  "signal_strength": 0.332985273865118,
  "confidence": 0.464412608686959,
  "coherence": 0.33586217286011827,
  "phi": 0.06626316505478408,
  "sl_price": 66655.90602203412,
  "tp_price": 66889.58795593178,
  "close_time": "2026-03-27T12:05:53.637697Z",
  "close_price": 66591.05,
  "result": "TRUE_NEGATIVE",
  "cycle_code": "CYC001_20260327",
  "candle_pos": "42",
  "swarm_intelligence": {
    "bull_agents": [
      "MomentumAgent",
      "CppFractalAgent",
      "FVGAgent",
      "PremiumDiscountAgent",
      "PriceGravityAgent",
      "AggressivenessAgent",
      "PriceVelocityAgent",
      "OscillationWaveAgent",
      "FeynmanPath",
      "ChaosRegime",
      "QuantumSpin",
      "ChaosFractalDim",
      "SpectralInformationFlux",
      "SingularSpectrumAnalysis",
      "KripkeSemantics",
      "RiemannianRicci"
    ],
    "bear_agents": [
      "TrendAgent",
      "MicrostructureAgent",
      "ReflexivityAgent",
      "LiquiditySiphonAgent",
      "MultiScaleFractalResonance",
      "OnChainPressureAgent",
      "MacroBiasAgent",
      "GameTheoryNashAgent",
      "BOSAgent",
      "ChartStructureAgent",
      "CandleAnatomyAgent",
      "PressureMatrix",
      "HexMatrix",
      "BlackSwanEVT",
      "Thermodynamic",
      "RiemannianManifold",
      "StrangeAttractorFolding",
      "FourierSpectral",
      "RandomMatrixTheory",
      "CrashVelocityDetector"
    ],
    "neutral_agents": [
      "VolumeAgent",
      "VolatilityAgent",
      "StatisticalAgent",
      "FractalAgent",
      "SRAgent",
      "DivergenceAgent",
      "ExplosionDetectorAgent",
      "MarketTransition",
      "SessionDynamics",
      "TemporalTrend",
      "WyckoffMatrix",
      "CRTAgent",
      "TBSAgent",
      "TensorMPS",
      "SpikingPulse",
      "MeanFieldGame",
      "QuantumSuperposition"
    ]
  },
  "snapshot": {
    "regime": "DRIFTING_BEAR",
    "atr": 51.92931864392578,
    "metadata": {
      "tick_velocity": 0.0,
      "v_pulse_detected": false,
      "shannon_entropy": 4.469047470876868,
      "jounce": 0.0
    }
  }
}