{
  "id": "GST_1774413600882",
  "status": "CLOSED",
  "entry_time": "2026-03-25T01:40:00.882255Z",
  "entry_timestamp": 1774413600.882255,
  "entry_price": 70641.21,
  "direction": "SELL",
  "veto_reason": "WAIT: SYNERGY_VETO (Φ=0.003)",
  "signal_strength": 0.0,
  "confidence": 0.47483062582755453,
  "coherence": 0.3571654358141909,
  "phi": 0.003012231545293797,
  "sl_price": 70714.14779649583,
  "tp_price": 70495.33440700835,
  "close_time": "2026-03-25T01:42:24.485860Z",
  "close_price": 70715.225,
  "result": "TRUE_NEGATIVE",
  "cycle_code": "CYC003_20260325",
  "candle_pos": "10_2",
  "swarm_intelligence": {
    "bull_agents": [
      "TrendAgent",
      "SRAgent",
      "LiquidationVacuumAgent",
      "StopHunterAgent",
      "MacroBiasAgent",
      "CppTickEntropyAgent",
      "ChartStructureAgent",
      "CandleAnatomyAgent",
      "BlackSwanEVT",
      "FeynmanPath",
      "ChaosRegime",
      "PheromoneFieldAgent",
      "RogueWaveNLSE",
      "HolographicEntanglement",
      "StrangeAttractorFolding",
      "MorphogeneticResonance",
      "RandomMatrixTheory",
      "DarkMatterGravity"
    ],
    "bear_agents": [
      "MomentumAgent",
      "MicrostructureAgent",
      "HarmonicResonanceAgent",
      "LiquiditySiphonAgent",
      "MultiScaleFractalResonance",
      "SentimentFearGreedAgent",
      "OnChainPressureAgent",
      "GameTheoryNashAgent",
      "CppFractalAgent",
      "PremiumDiscountAgent",
      "PriceVelocityAgent",
      "PressureMatrix",
      "TemporalTrend",
      "HexMatrix",
      "Thermodynamic",
      "RiemannianManifold",
      "QuantumSpin",
      "ChaosFractalDim",
      "SpectralInformationFlux",
      "SingularSpectrumAnalysis",
      "RiemannianRicci",
      "KolmogorovInertia"
    ],
    "neutral_agents": [
      "VolumeAgent",
      "VolatilityAgent",
      "StatisticalAgent",
      "FractalAgent",
      "DivergenceAgent",
      "TimeWarpAgent",
      "PriceGravityAgent",
      "AggressivenessAgent",
      "ExplosionDetectorAgent",
      "OscillationWaveAgent",
      "MarketTransition",
      "SessionDynamics",
      "WyckoffMatrix",
      "CRTAgent",
      "TBSAgent",
      "MarketIntuition",
      "TensorMPS",
      "SpikingPulse",
      "MeanFieldGame",
      "HolographicManifold",
      "InformationGeometry",
      "QuantumSuperposition",
      "RGScalingInvariance"
    ]
  },
  "snapshot": {
    "regime": "CHOPPY",
    "atr": 48.62519766388423,
    "metadata": {
      "tick_velocity": 4.186552792430713,
      "v_pulse_detected": false,
      "shannon_entropy": 5.440482725389749,
      "jounce": 5.205976478863569
    }
  }
}